openpiv_python_lite/__init__.py
openpiv_python_lite/pyprocess.py
openpiv_python_lite-0.1.dist-info/METADATA
openpiv_python_lite-0.1.dist-info/WHEEL
openpiv_python_lite-0.1.dist-info/top_level.txt
openpiv_python_lite-0.1.dist-info/RECORD
