Metadata-Version: 2.1
Name: openpiv-python-lite
Version: 0.1
Summary: Lightweight version of OpenPIV-Python
Home-page: http://github.com/openpiv/openpiv_python_lite
Author: Alex Liberzon
Author-email: alex.liberzon@gmail.com
License: MIT
Platform: UNKNOWN
